csv2mysql/__init__.py
csv2mysql/__main__.py
csv2mysql/csv2mysql.py
csv2mysql-0.0.2.dist-info/DESCRIPTION.rst
csv2mysql-0.0.2.dist-info/METADATA
csv2mysql-0.0.2.dist-info/RECORD
csv2mysql-0.0.2.dist-info/WHEEL
csv2mysql-0.0.2.dist-info/entry_points.txt
csv2mysql-0.0.2.dist-info/metadata.json
csv2mysql-0.0.2.dist-info/top_level.txt
